sonar_software_api/__init__.py
sonar_software_api/client.py
sonar_software_api-0.1.8.dist-info/METADATA
sonar_software_api-0.1.8.dist-info/WHEEL
sonar_software_api-0.1.8.dist-info/top_level.txt
sonar_software_api-0.1.8.dist-info/RECORD
