Metadata-Version: 2.4
Name: sonar_software_api
Version: 0.1.8
Summary: A simple GraphQL client for interacting with your Sonar Software instance
Author: JckHamm3r
Requires-Python: >=3.7
Requires-Dist: gql>=3.4.0
Requires-Dist: requests_toolbelt>=1.0.0
Dynamic: author
Dynamic: requires-dist
Dynamic: requires-python
Dynamic: summary
